smartportfolio/__init__.py
smartportfolio/__main__.py
smartportfolio/app.py
smartportfolio/config.py
smartportfolio/pipeline.py
smartportfolio/visualization.py
smartportfolio/data/__init__.py
smartportfolio/data/features.py
smartportfolio/data/fetcher.py
smartportfolio/data/preprocessor.py
smartportfolio/data/storage.py
smartportfolio/forecast/__init__.py
smartportfolio/forecast/prophet_model.py
smartportfolio/graph/__init__.py
smartportfolio/graph/builder.py
smartportfolio/graph/dgl_gat.py
smartportfolio/graph/gat.py
smartportfolio/graph/torch_gat.py
smartportfolio/rl/__init__.py
smartportfolio/rl/agent.py
smartportfolio/rl/environment.py
smartportfolio/rl/rewards.py
smartportfolio/ui/__init__.py
smartportfolio/ui/styles.py
smartportfolio/ui/components/__init__.py
smartportfolio/utils/__init__.py
smartportfolio/utils/memory.py
smartportfolio-2.1.5.dist-info/licenses/LICENSE
smartportfolio-2.1.5.dist-info/METADATA
smartportfolio-2.1.5.dist-info/WHEEL
smartportfolio-2.1.5.dist-info/entry_points.txt
smartportfolio-2.1.5.dist-info/top_level.txt
smartportfolio-2.1.5.dist-info/RECORD
