Metadata-Version: 2.4
Name: smartportfolio
Version: 2.1.5
Summary: GNN + Prophet + DRL Portfolio Optimization TUI - A terminal-based intelligent asset allocation system
Author: Anonymous
License: MIT
Project-URL: Homepage, https://github.com/Ronit26Mehta/SmartPortfolio
Project-URL: Documentation, https://github.com/Ronit26Mehta/SmartPortfolio#readme
Project-URL: Repository, https://github.com/Ronit26Mehta/SmartPortfolio
Keywords: portfolio-optimization,graph-neural-network,reinforcement-learning,prophet,tui,terminal,finance,asset-allocation
Classifier: Development Status :: 5 - Production/Stable
Classifier: Environment :: Console
Classifier: Intended Audience :: Financial and Insurance Industry
Classifier: License :: OSI Approved :: MIT License
Classifier: Operating System :: OS Independent
Classifier: Programming Language :: Python :: 3
Classifier: Programming Language :: Python :: 3.10
Classifier: Programming Language :: Python :: 3.11
Classifier: Programming Language :: Python :: 3.12
Classifier: Topic :: Office/Business :: Financial :: Investment
Classifier: Topic :: Scientific/Engineering :: Artificial Intelligence
Requires-Python: >=3.10
License-File: LICENSE
Requires-Dist: numpy>=1.24.0
Requires-Dist: pandas>=2.0.0
Requires-Dist: scipy>=1.10.0
Requires-Dist: networkx>=3.0
Requires-Dist: scikit-learn>=1.3.0
Requires-Dist: textual>=0.40.0
Requires-Dist: rich>=13.0.0
Requires-Dist: yfinance>=0.2.30
Requires-Dist: openpyxl>=3.1.0
Requires-Dist: prophet>=1.1.0
Requires-Dist: stable-baselines3>=2.0.0
Requires-Dist: gymnasium>=0.29.0
Requires-Dist: torch>=2.0.0
Requires-Dist: matplotlib>=3.7.0
Requires-Dist: plotext>=5.2.0
Provides-Extra: dev
Requires-Dist: pytest>=7.0.0; extra == "dev"
Requires-Dist: pytest-cov>=4.0.0; extra == "dev"
Requires-Dist: black>=23.0.0; extra == "dev"
Requires-Dist: ruff>=0.1.0; extra == "dev"
Dynamic: license-file
